odoo/addons/test_ssi_transaction_mixin/README.rst
odoo/addons/test_ssi_transaction_mixin/__init__.py
odoo/addons/test_ssi_transaction_mixin/__manifest__.py
odoo/addons/test_ssi_transaction_mixin/data/approval_template_data.xml
odoo/addons/test_ssi_transaction_mixin/data/ir_sequence_data.xml
odoo/addons/test_ssi_transaction_mixin/data/policy_template_data.xml
odoo/addons/test_ssi_transaction_mixin/data/sequence_template_data.xml
odoo/addons/test_ssi_transaction_mixin/models/__init__.py
odoo/addons/test_ssi_transaction_mixin/models/test_transaction_detail_mixin.py
odoo/addons/test_ssi_transaction_mixin/models/test_transaction_mixin.py
odoo/addons/test_ssi_transaction_mixin/models/test_transaction_mixin_inherit.py
odoo/addons/test_ssi_transaction_mixin/security/ir.model.access.csv
odoo/addons/test_ssi_transaction_mixin/static/description/icon.png
odoo/addons/test_ssi_transaction_mixin/views/test_transaction_mixin_inherit_view.xml
odoo/addons/test_ssi_transaction_mixin/views/test_transaction_mixin_view.xml
odoo14_addon_test_ssi_transaction_mixin-14.0.1.1.0.dist-info/METADATA
odoo14_addon_test_ssi_transaction_mixin-14.0.1.1.0.dist-info/WHEEL
odoo14_addon_test_ssi_transaction_mixin-14.0.1.1.0.dist-info/top_level.txt
odoo14_addon_test_ssi_transaction_mixin-14.0.1.1.0.dist-info/RECORD
